{
  "testConfigName": "calculatorConfig",

  "appIconName": "Calculator",

  "packageOrBundleId": "com.google.android.calculator",

  "startupPackageOrBundleId": "com.google.android.calculator",
  "startupActivity": "com.android.calculator2.Calculator",

  "dataset": {
    "apps": "testConfig/android/calculator/dataset/apps.json"
  },

  "capabilities": {
    "automationName": "UiAutomator2",
    "platformName": "Android",
    "language": "en",
    "locale": "US"
  },

  "profiles": [
    {
      "profileName": "Android *",
      "capabilities": {
        "platformVersion": "*"
      }
    },
    {
      "profileName": "Android 12",
      "capabilities": {
        "platformVersion": "12"
      }
    },    {
      "profileName": "Pixel 3a(Android 12)",
      "specialTags": "Tag2, Tag3",
      "capabilities": {
      }
    },
    {
      "profileName": "Android 11",
      "capabilities": {
        "platformVersion": "11"
      }
    },



    {
      "profileName": "Pixel 3a(Android 12)-01",
      "capabilities": {
        "systemPort": "8201"
      }
    },
    {
      "profileName": "Pixel 3a(Android 12)-02",
      "capabilities": {
        "systemPort": "8202"
      }
    },
    {
      "profileName": "Pixel 3a(Android 12)-03",
      "capabilities": {
        "systemPort": "8203"
      }
    },
    {
      "profileName": "Pixel 3a(Android 12)-04",
      "capabilities": {
        "systemPort": "8204"
      }
    },
    {
      "profileName": "Pixel 3a(Android 12)-05",
      "capabilities": {
        "systemPort": "8205"
      }
    },
    {
      "profileName": "Pixel 3a(Android 12)-06",
      "capabilities": {
        "systemPort": "8206"
      }
    },
    {
      "profileName": "Pixel 3a(Android 12)-07",
      "capabilities": {
        "systemPort": "8207"
      }
    },
    {
      "profileName": "Pixel 3a(Android 12)-08",
      "capabilities": {
        "systemPort": "8208"
      }
    }
  ]
}